aipack/__init__.py
aipack/anchor.py
aipack/converter.py
aipack/data.py
aipack/model.py
aipack/tf.py
aipack/util.py
aipack-0.0.5.dist-info/LICENSE
aipack-0.0.5.dist-info/METADATA
aipack-0.0.5.dist-info/WHEEL
aipack-0.0.5.dist-info/top_level.txt
aipack-0.0.5.dist-info/RECORD
