Metadata-Version: 2.1
Name: aipack
Version: 0.0.5
Summary: AI Package
Home-page: https://github.com/heewinkim/aipack
Author: HEESEUNG KIM
Author-email: heewin.kim@gmail.com
License: MIT
Download-URL: https://github.com/heewinkim/aipack/archive/master.zip
Platform: UNKNOWN
Classifier: Programming Language :: Python :: 3
Classifier: License :: OSI Approved :: MIT License
Classifier: Operating System :: OS Independent
Requires-Python: >=3.6.1
Requires-Dist: tensorflow (==2.0.0)
Requires-Dist: utilpack
